{
"type": "FeatureCollection",
"name": "leftRoadblocks",
"crs": { "type": "name", "properties": { "name": "urn:ogc:def:crs:OGC:1.3:CRS84" } },
"features": [
{ "type": "Feature", "properties": { }, "geometry": { "type": "Point", "coordinates": [ 9.95760820449363, 53.570032063897919 ] } },
{ "type": "Feature", "properties": { }, "geometry": { "type": "Point", "coordinates": [ 9.958527050293899, 53.567571928368167 ] } },
{ "type": "Feature", "properties": { }, "geometry": { "type": "Point", "coordinates": [ 9.962232073682081, 53.565419309779635 ] } },
{ "type": "Feature", "properties": { }, "geometry": { "type": "Point", "coordinates": [ 9.962261713869186, 53.564322622856729 ] } },
{ "type": "Feature", "properties": { }, "geometry": { "type": "Point", "coordinates": [ 9.963017538640376, 53.562170004268197 ] } },
{ "type": "Feature", "properties": { }, "geometry": { "type": "Point", "coordinates": [ 9.962143153120765, 53.56176986174227 ] } },
{ "type": "Feature", "properties": { }, "geometry": { "type": "Point", "coordinates": [ 9.9636992629438, 53.559809904369921 ] } },
{ "type": "Feature", "properties": { }, "geometry": { "type": "Point", "coordinates": [ 9.964158685843936, 53.559128180066502 ] } },
{ "type": "Feature", "properties": { }, "geometry": { "type": "Point", "coordinates": [ 9.967211625115798, 53.557390524097443 ] } },
{ "type": "Feature", "properties": { }, "geometry": { "type": "Point", "coordinates": [ 9.96987924195529, 53.554748842421667 ] } },
{ "type": "Feature", "properties": { }, "geometry": { "type": "Point", "coordinates": [ 9.972635779356098, 53.553829996621396 ] } },
{ "type": "Feature", "properties": { }, "geometry": { "type": "Point", "coordinates": [ 9.973599085437025, 53.549824866338774 ] } },
{ "type": "Feature", "properties": { }, "geometry": { "type": "Point", "coordinates": [ 9.972769160198071, 53.54756850709537 ] } },
{ "type": "Feature", "properties": { }, "geometry": { "type": "Point", "coordinates": [ 9.972480168373792, 53.545508514091537 ] } }
]
}
