{
"type": "FeatureCollection",
"name": "kellinghusenstraße_switchh",
"crs": { "type": "name", "properties": { "name": "urn:ogc:def:crs:OGC:1.3:CRS84" } },
"features": [
{ "type": "Feature", "properties": { }, "geometry": { "type": "Point", "coordinates": [ 9.991009858636433, 53.58934938204825 ] } },
{ "type": "Feature", "properties": { }, "geometry": { "type": "Point", "coordinates": [ 9.991051764312154, 53.589348153940463 ] } },
{ "type": "Feature", "properties": { }, "geometry": { "type": "Point", "coordinates": [ 9.991101971973107, 53.589348153940463 ] } }
]
}
